kerno/__init__.py
kerno/action.py
kerno/colander.py
kerno/dataclass.py
kerno/email/__init__.py
kerno/email/pyramid.py
kerno/email/pyramid_mailer.py
kerno/event.py
kerno/kerno.py
kerno/peto.py
kerno/pydantic.py
kerno/repository/__init__.py
kerno/repository/sqlalchemy.py
kerno/start.py
kerno/state.py
kerno/typing.py
kerno/utility_registry.py
kerno/web/__init__.py
kerno/web/jsonright.py
kerno/web/kerno.js
kerno/web/malbona.jinja2
kerno/web/msg_to_html.py
kerno/web/pyramid/__init__.py
kerno/web/pyramid/typing.py
kerno/web/to_dict.py
kerno-0.8.0.dist-info/WHEEL
kerno-0.8.0.dist-info/METADATA
kerno-0.8.0.dist-info/RECORD
