Metadata-Version: 2.1
Name: kerno
Version: 0.8.0
Summary: Framework for the application service layer.
Home-page: https://github.com/nandoflorestan/kerno
License: MIT
Keywords: Clean Architecture,service layer,action,pyramid,sqlalchemy
Author: Nando Florestan
Author-email: nandoflorestan@gmail.com
Requires-Python: >=3.9
Classifier: Development Status :: 4 - Beta
Classifier: Framework :: Pyramid
Classifier: Intended Audience :: Developers
Classifier: License :: OSI Approved :: MIT License
Classifier: Operating System :: OS Independent
Classifier: Programming Language :: Python
Classifier: Programming Language :: Python :: 3
Classifier: Programming Language :: Python :: 3.9
Classifier: Programming Language :: Python :: 3.10
Classifier: Programming Language :: Python :: 3
Classifier: Programming Language :: Python :: 3.10
Classifier: Programming Language :: Python :: 3.11
Classifier: Programming Language :: Python :: 3.9
Classifier: Programming Language :: Python :: Implementation :: CPython
Classifier: Programming Language :: Python :: Implementation :: PyPy
Classifier: Topic :: Database
Classifier: Topic :: Internet :: WWW/HTTP
Classifier: Topic :: Internet :: WWW/HTTP :: WSGI
Classifier: Topic :: Software Development :: Libraries
Classifier: Topic :: Software Development :: Libraries :: Application Frameworks
Requires-Dist: bag (>=5.0)
Requires-Dist: reg (==0.12)
Project-URL: Documentation, http://docs.nando.audio/kerno/latest/
Project-URL: Repository, https://github.com/nandoflorestan/kerno
